girder_virtual_resources/__init__.py
girder_virtual_resources/rest/__init__.py
girder_virtual_resources/rest/virtual_file.py
girder_virtual_resources/rest/virtual_folder.py
girder_virtual_resources/rest/virtual_item.py
girder_virtual_resources/rest/virtual_resource.py
girder_virtual_resources/web_client/dist/girder-plugin-virtual-resources.umd.cjs
girder_virtual_resources/web_client/dist/style.css
girder_virtual_resources-2.1.1.dist-info/licenses/LICENSE
girder_virtual_resources-2.1.1.dist-info/METADATA
girder_virtual_resources-2.1.1.dist-info/WHEEL
girder_virtual_resources-2.1.1.dist-info/entry_points.txt
girder_virtual_resources-2.1.1.dist-info/top_level.txt
girder_virtual_resources-2.1.1.dist-info/RECORD
